LICENSE
MANIFEST.in
README.md
pyproject.toml
setup.cfg
setup.py
dash_security.egg-info/PKG-INFO
dash_security.egg-info/SOURCES.txt
dash_security.egg-info/dependency_links.txt
dash_security.egg-info/top_level.txt
security/__init__.py