Metadata-Version: 2.1
Name: dash-security
Version: 0.1.14
Summary: Building blocks for secure Dash development with Dash Pages
License-File: LICENSE
